matplotsklib/__init__.py
matplotsklib/__main__.py
matplotsklib-0.1.dist-info/METADATA
matplotsklib-0.1.dist-info/WHEEL
matplotsklib-0.1.dist-info/entry_points.txt
matplotsklib-0.1.dist-info/top_level.txt
matplotsklib-0.1.dist-info/RECORD
